SpamKit/__init__.py
SpamKit/spamkit.py
spamkit-0.1.1.dist-info/METADATA
spamkit-0.1.1.dist-info/WHEEL
spamkit-0.1.1.dist-info/top_level.txt
spamkit-0.1.1.dist-info/RECORD
