Metadata-Version: 2.4
Name: SpamKit
Version: 0.1.1
Summary: A utility library for sending emails (legitimate use).
Author: JACK
Author-email: gsksvsksksj@gmail.com
Classifier: Programming Language :: Python :: 3
Classifier: License :: OSI Approved :: MIT License
Classifier: Operating System :: OS Independent
Requires-Python: >=3.6
Requires-Dist: requests
Requires-Dist: user-agent
Dynamic: author
Dynamic: author-email
Dynamic: classifier
Dynamic: description
Dynamic: description-content-type
Dynamic: requires-dist
Dynamic: requires-python
Dynamic: summary
